OGRePy/__init__.py
OGRePy/_core.py
OGRePy/abc.py
OGRePy/py.typed
OGRePy/docs/OGRePy_Documentation.html
OGRePy/docs/OGRePy_Documentation.ipynb
OGRePy/docs/OGRePy_Documentation.pdf
ogrepy-1.3.1.dist-info/licenses/LICENSE.txt
ogrepy-1.3.1.dist-info/METADATA
ogrepy-1.3.1.dist-info/WHEEL
ogrepy-1.3.1.dist-info/top_level.txt
ogrepy-1.3.1.dist-info/RECORD
