Metadata-Version: 2.4
Name: OGRePy
Version: 1.3.1
Summary: An Object-Oriented General Relativity Package for Python
Author-email: Barak Shoshany <baraksh@gmail.com>
Maintainer-email: Barak Shoshany <baraksh@gmail.com>
License: MIT License
Project-URL: Changelog, https://github.com/bshoshany/OGRePy/blob/master/CHANGELOG.md
Project-URL: Documentation, https://github.com/bshoshany/OGRePy/blob/master/README.md
Project-URL: Homepage, https://github.com/bshoshany/OGRePy
Project-URL: Issues, https://github.com/bshoshany/OGRePy/issues
Project-URL: Source, https://github.com/bshoshany/OGRePy
Keywords: differential geometry,general relativity,mathematics,physics,scientific computing,tensor,tensors
Classifier: Development Status :: 5 - Production/Stable
Classifier: Framework :: IPython
Classifier: Framework :: Jupyter :: JupyterLab :: 4
Classifier: Framework :: Jupyter :: JupyterLab
Classifier: Framework :: Jupyter
Classifier: Intended Audience :: Science/Research
Classifier: License :: OSI Approved :: MIT License
Classifier: Operating System :: OS Independent
Classifier: Programming Language :: Python :: 3 :: Only
Classifier: Programming Language :: Python :: 3
Classifier: Programming Language :: Python :: 3.12
Classifier: Programming Language :: Python :: 3.13
Classifier: Programming Language :: Python
Classifier: Topic :: Scientific/Engineering :: Astronomy
Classifier: Topic :: Scientific/Engineering :: Mathematics
Classifier: Topic :: Scientific/Engineering :: Physics
Classifier: Topic :: Scientific/Engineering
Classifier: Typing :: Typed
Requires-Python: >=3.12
License-File: LICENSE.txt
Requires-Dist: ipykernel>=6.9.2
Requires-Dist: sympy>=1.12
Dynamic: license-file
